cli/__init__.py
cli/app.py
cli/exceptions.py
cli/commands/__init__.py
cli/commands/check.py
cli/commands/schema.py
cli/core/__init__.py
cli/core/config.py
cli/core/data_validator.py
cli/core/error_classifier.py
cli/core/error_handler.py
cli/core/exception_handler.py
cli/core/output_formatter.py
cli/core/rule_parser.py
cli/core/source_parser.py
core/__init__.py
core/config.py
core/engine/prevalidation.py
core/engine/rule_engine.py
core/engine/rule_merger.py
core/executors/__init__.py
core/executors/base_executor.py
core/executors/completeness_executor.py
core/executors/schema_executor.py
core/executors/uniqueness_executor.py
core/executors/validity_executor.py
core/registry/__init__.py
core/registry/builtin_rule_types.py
core/registry/rule_type_registry.py
shared/__init__.py
shared/config/__init__.py
shared/config/loader.py
shared/config/logging_config.py
shared/database/__init__.py
shared/database/connection.py
shared/database/database_dialect.py
shared/database/query_executor.py
shared/database/sqlite_functions.py
shared/enums/__init__.py
shared/enums/connection_types.py
shared/enums/data_types.py
shared/enums/execution_status.py
shared/enums/rule_actions.py
shared/enums/rule_categories.py
shared/enums/rule_types.py
shared/enums/severity_levels.py
shared/exceptions/__init__.py
shared/exceptions/exception_system.py
shared/schema/__init__.py
shared/schema/base.py
shared/schema/connection_schema.py
shared/schema/result_schema.py
shared/schema/rule_schema.py
shared/utils/__init__.py
shared/utils/console.py
shared/utils/datetime_utils.py
shared/utils/error_handler.py
shared/utils/logger.py
shared/utils/logging_setup.py
shared/utils/model_helpers.py
shared/utils/param_converter.py
shared/utils/type_parser.py
validatelite-0.5.0.dist-info/licenses/LICENSE
validatelite-0.5.0.dist-info/METADATA
validatelite-0.5.0.dist-info/WHEEL
validatelite-0.5.0.dist-info/entry_points.txt
validatelite-0.5.0.dist-info/top_level.txt
validatelite-0.5.0.dist-info/RECORD
