Metadata-Version: 2.4
Name: validatelite
Version: 0.5.0
Summary: A flexible, extensible command-line tool for automated data quality validation
Author-email: Your Name <your.email@example.com>
Maintainer-email: Your Name <your.email@example.com>
License: MIT
Project-URL: Homepage, https://github.com/litedatum/validatelite
Project-URL: Documentation, https://github.com/litedatum/validatelite#readme
Project-URL: Repository, https://github.com/litedatum/validatelite.git
Project-URL: Bug Tracker, https://github.com/litedatum/validatelite/issues
Project-URL: Release Notes, https://github.com/litedatum/validatelite/blob/main/CHANGELOG.md
Keywords: data-quality,validation,cli,database,data-engineering
Classifier: Development Status :: 4 - Beta
Classifier: Intended Audience :: Developers
Classifier: Intended Audience :: Information Technology
Classifier: License :: OSI Approved :: MIT License
Classifier: Operating System :: OS Independent
Classifier: Programming Language :: Python :: 3
Classifier: Programming Language :: Python :: 3.8
Classifier: Programming Language :: Python :: 3.9
Classifier: Programming Language :: Python :: 3.10
Classifier: Programming Language :: Python :: 3.11
Classifier: Topic :: Database
Classifier: Topic :: Scientific/Engineering :: Information Analysis
Classifier: Topic :: Software Development :: Libraries :: Python Modules
Requires-Python: >=3.8
License-File: LICENSE
Requires-Dist: click>=8.0.0
Requires-Dist: pandas>=2.0.0
Requires-Dist: sqlalchemy[asyncio]>=2.0.0
Requires-Dist: pydantic>=2.0.0
Requires-Dist: python-dotenv>=1.0.0
Requires-Dist: rich>=13.0.0
Requires-Dist: aiomysql>=0.2.0
Requires-Dist: asyncpg>=0.29.0
Requires-Dist: aiosqlite>=0.19.0
Requires-Dist: mysqlclient>=2.2.0
Requires-Dist: psycopg2-binary>=2.9.0
Requires-Dist: python-dateutil>=2.8.0
Requires-Dist: pytz>=2024.1
Provides-Extra: dev
Requires-Dist: pytest>=8.0.0; extra == "dev"
Requires-Dist: pytest-asyncio>=0.23.0; extra == "dev"
Requires-Dist: pytest-cov>=4.1.0; extra == "dev"
Requires-Dist: pytest-mock>=3.11.0; extra == "dev"
Requires-Dist: black>=24.2.0; extra == "dev"
Requires-Dist: isort>=5.13.0; extra == "dev"
Requires-Dist: flake8>=7.0.0; extra == "dev"
Requires-Dist: mypy>=1.8.0; extra == "dev"
Requires-Dist: pre-commit>=3.6.0; extra == "dev"
Requires-Dist: bandit>=1.7.5; extra == "dev"
Requires-Dist: safety>=2.3.5; extra == "dev"
Requires-Dist: hypothesis>=6.88.0; extra == "dev"
Requires-Dist: openpyxl>=3.1.0; extra == "dev"
Requires-Dist: pandas-stubs>=2.2.0; extra == "dev"
Requires-Dist: pylint>=2.17.0; extra == "dev"
Requires-Dist: sphinx>=7.0.0; extra == "dev"
Requires-Dist: sphinx-rtd-theme>=1.2.0; extra == "dev"
Requires-Dist: psutil>=5.9.0; extra == "dev"
Requires-Dist: sqlalchemy-stubs>=0.4; extra == "dev"
Requires-Dist: types-psutil>=6.9.0; extra == "dev"
Requires-Dist: types-python-dateutil>=2.8.19; extra == "dev"
Requires-Dist: types-pytz>=2023.3.1; extra == "dev"
Requires-Dist: types-PyYAML>=6.0.12; extra == "dev"
Requires-Dist: types-requests>=2.31.0; extra == "dev"
Requires-Dist: types-setuptools>=68.1.0; extra == "dev"
Requires-Dist: types-six>=1.16.21; extra == "dev"
Requires-Dist: types-toml>=0.10.8; extra == "dev"
Dynamic: license-file
